[{"Timestamp":"00:00:00","Token":"ゆる 言語学ラジオ","Speaker":null},{"Timestamp":"00:00:03","Token":"あ、ちょっとオープニング間違えたんで","Speaker":null},{"Timestamp":"00:00:06","Token":"なに?","Speaker":null},{"Timestamp":"00:00:07","Token":"やり直していいですか?","Speaker":null},{"Timestamp":"00:00:08","Token":"いやいや間違えるもん何も","Speaker":null},{"Timestamp":"00:00:10","Token":"いやオープニング間違えたんでやり直します","Speaker":null},{"Timestamp":"00:00:12","Token":"はい","Speaker":null},{"Timestamp":"00:00:13","Token":"ゆる コンピューター科学ラジオ","Speaker":null},{"Timestamp":"00:00:16","Token":"ということで今回は","Speaker":null},{"Timestamp":"00:00:18","Token":"ゆる コンピューター科学ラジオです","Speaker":null},{"Timestamp":"00:00:21","Token":"え、乗っ取られた?","Speaker":null},{"Timestamp":"00:00:22","Token":"そうジャックしに来ましたチャンネル","Speaker":null},{"Timestamp":"00:00:24","Token":"ちょっともうダメだ言語学は","Speaker":null},{"Timestamp":"00:00:27","Token":"コンピューター科学でジャックしたいなという欲求があったんで","Speaker":null},{"Timestamp":"00:00:31","Token":"結構ね言語の話をしてる時にコンピューター科学の知識使ったり","Speaker":null},{"Timestamp":"00:00:36","Token":"例えがちだったり","Speaker":null},{"Timestamp":"00:00:37","Token":"ちょっとここらでそろそろ僕に通り一遍の知識を入れてからの方が","Speaker":null},{"Timestamp":"00:00:42","Token":"議論が整理されるかもしれないですもんね","Speaker":null},{"Timestamp":"00:00:43","Token":"まさにそういうことで","Speaker":null},{"Timestamp":"00:00:45","Token":"前なんかの回で","Speaker":null},{"Timestamp":"00:00:47","Token":"プログラミング言語は言語じゃないですからねみたいなことを","Speaker":null},{"Timestamp":"00:00:50","Token":"みずのさんが言って","Speaker":null},{"Timestamp":"00:00:51","Token":"え、そんなことないでしょみたいな僕は言って","Speaker":null},{"Timestamp":"00:00:54","Token":"ただみずのさんがプログラミング言語の知識がなさすぎて","Speaker":null},{"Timestamp":"00:01:00","Token":"建設的な議論に全くならなそうだったんですよね","Speaker":null},{"Timestamp":"00:01:04","Token":"コメント欄でもその話聞きたかったって話が結構ありまして","Speaker":null},{"Timestamp":"00:01:09","Token":"だったらやったろうということで","Speaker":null},{"Timestamp":"00:01:12","Token":"駆け足ですね","Speaker":null},{"Timestamp":"00:01:13","Token":"多分前3回で","Speaker":null},{"Timestamp":"00:01:15","Token":"プログラミング言語とは何かをみずのさんに理解してもらう","Speaker":null},{"Timestamp":"00:01:19","Token":"という回にしたいと思います","Speaker":null},{"Timestamp":"00:01:21","Token":"リスナーさん妙にコンピューター言語に詳しそうな人ばっかコメントにいるけど","Speaker":null},{"Timestamp":"00:01:26","Token":"おそらく聞いてる人の中でコメントをしないほとんどの人はそんなに詳しくないと思います","Speaker":null},{"Timestamp":"00:01:30","Token":"と思いますね","Speaker":null},{"Timestamp":"00:01:31","Token":"ただ一個断っておきたいのは","Speaker":null},{"Timestamp":"00:01:33","Token":"昨今プログラミング言語教育の重要性が叫ばれてまして","Speaker":null},{"Timestamp":"00:01:41","Token":"だからみずのさんってマジで何も知らないじゃないですか","Speaker":null},{"Timestamp":"00:01:45","Token":"ソースコードって言ってましたよね","Speaker":null},{"Timestamp":"00:01:46","Token":"言ってましたね","Speaker":null},{"Timestamp":"00:01:47","Token":"いやわかんないですソースコード","Speaker":null},{"Timestamp":"00:01:50","Token":"そのレベルの人は多分会員2割とか3割とかだと思う","Speaker":null},{"Timestamp":"00:01:55","Token":"俺262のうちの2?","Speaker":null},{"Timestamp":"00:01:58","Token":"そうパレートの法則でいう会員の働かないあり","Speaker":null},{"Timestamp":"00:02:02","Token":"そんな低いの?","Speaker":null},{"Timestamp":"00:02:03","Token":"実験で取り除かれるタイプのあり","Speaker":null},{"Timestamp":"00:02:05","Token":"僕今でも聞いてくれてる自分の友達でソースコードわかってる人一人もいないかもしれない","Speaker":null},{"Timestamp":"00:02:12","Token":"じゃあちょっと僕の見積もりがおかしいかもしれないですけど","Speaker":null},{"Timestamp":"00:02:15","Token":"僕はそうなんじゃないかなと思ってまして","Speaker":null},{"Timestamp":"00:02:18","Token":"だってあれでしょウェブサイトとか全く作ったことないし","Speaker":null},{"Timestamp":"00:02:22","Token":"HTMLって何?みたいな感じですね","Speaker":null},{"Timestamp":"00:02:26","Token":"よくわかんないよねあれでHTMLでくれとか言われても","Speaker":null},{"Timestamp":"00:02:29","Token":"知らねえよ","Speaker":null},{"Timestamp":"00:02:30","Token":"何それっていう状態なわけですよね","Speaker":null},{"Timestamp":"00:02:31","Token":"リンク送ればいいだろっていう感じですね","Speaker":null},{"Timestamp":"00:02:34","Token":"という状態から脱するための構造をちょっとやりたいなと思いまして","Speaker":null},{"Timestamp":"00:02:39","Token":"鬼本さん僕に優しく教えてくれる時も","Speaker":null},{"Timestamp":"00:02:42","Token":"わかんない単語使って教えてくること多いんで","Speaker":null},{"Timestamp":"00:02:44","Token":"先に注意しておきますね","Speaker":null},{"Timestamp":"00:02:46","Token":"ソースコードですよこれとか言われてもわかんないから","Speaker":null},{"Timestamp":"00:02:48","Token":"ハァってなるからね","Speaker":null},{"Timestamp":"00:02:49","Token":"頼みますよ本当","Speaker":null},{"Timestamp":"00:02:50","Token":"その度止めていただければ","Speaker":null},{"Timestamp":"00:02:51","Token":"わかりました","Speaker":null},{"Timestamp":"00:02:52","Token":"一応舌打ちしながら教えます","Speaker":null},{"Timestamp":"00:02:55","Token":"嫌な教官だな","Speaker":null},{"Timestamp":"00:02:59","Token":"とりあえず初回の目標なんですけど","Speaker":null},{"Timestamp":"00:03:01","Token":"技術が全然できない人あるあるで","Speaker":null},{"Timestamp":"00:03:04","Token":"パソコンとかスマホの中身","Speaker":null},{"Timestamp":"00:03:07","Token":"魔法だと思いがち","Speaker":null},{"Timestamp":"00:03:11","Token":"確かにね","Speaker":null},{"Timestamp":"00:03:14","Token":"おかしいもんね","Speaker":null},{"Timestamp":"00:03:15","Token":"このサイズにあの機能がたくさん搭載されてること","Speaker":null},{"Timestamp":"00:03:18","Token":"やばいじゃないですか","Speaker":null},{"Timestamp":"00:03:19","Token":"僕でも一つだけ知識ありますよ","Speaker":null},{"Timestamp":"00:03:21","Token":"どうやら反動体ってのがすごいらしい","Speaker":null},{"Timestamp":"00:03:23","Token":"そうなんですよ","Speaker":null},{"Timestamp":"00:03:24","Token":"いやおっしゃる通りで","Speaker":null},{"Timestamp":"00:03:25","Token":"反動体が何十億個とかもっとだわ","Speaker":null},{"Timestamp":"00:03:28","Token":"何兆個とか詰まってる","Speaker":null},{"Timestamp":"00:03:30","Token":"おかげでああいうことができてる","Speaker":null},{"Timestamp":"00:03:31","Token":"なんか式法を読んでる時に","Speaker":null},{"Timestamp":"00:03:34","Token":"覚えましたその知識","Speaker":null},{"Timestamp":"00:03:36","Token":"会社式法とか業界地図読んでる時に","Speaker":null},{"Timestamp":"00:03:38","Token":"素晴らしいです","Speaker":null},{"Timestamp":"00:03:40","Token":"反動体はすごいよ","Speaker":null},{"Timestamp":"00:03:41","Token":"でも動体と反動体と絶縁体のうちの反動体でしょ","Speaker":null},{"Timestamp":"00:03:45","Token":"何がそんなすごいのっていう感じですね","Speaker":null},{"Timestamp":"00:03:47","Token":"いやだってシリコンバレーのシリコンって","Speaker":null},{"Timestamp":"00:03:49","Token":"反動体ですからね","Speaker":null},{"Timestamp":"00:03:51","Token":"全てが反動体","Speaker":null},{"Timestamp":"00:03:52","Token":"本当にそうなんですけど","Speaker":null},{"Timestamp":"00:03:53","Token":"コンピューターの本質を取り出して分解していくと","Speaker":null},{"Timestamp":"00:03:55","Token":"反動体でしかないんですよ","Speaker":null},{"Timestamp":"00:03:57","Token":"そうなんだ","Speaker":null},{"Timestamp":"00:03:58","Token":"結局反動体の組み合わせなんですよ","Speaker":null},{"Timestamp":"00:04:01","Token":"ということで僕は大学でコンピューターサインスやったので","Speaker":null},{"Timestamp":"00:04:05","Token":"一応物理的に何が起きてるかぐらいの","Speaker":null},{"Timestamp":"00:04:08","Token":"なんとなくのイメージはあるんです","Speaker":null},{"Timestamp":"00:04:09","Token":"なんとなくじゃないな","Speaker":null},{"Timestamp":"00:04:10","Token":"正しいイメージがあるんですよ","Speaker":null},{"Timestamp":"00:04:12","Token":"こういうことが起きてるから","Speaker":null},{"Timestamp":"00:04:13","Token":"こういういろんな奇跡のようなことができるんだな","Speaker":null},{"Timestamp":"00:04:16","Token":"じゃあコンピューターの中身なんとなく想像いってるってことですか","Speaker":null},{"Timestamp":"00:04:19","Token":"想像いってるところか","Speaker":null},{"Timestamp":"00:04:20","Token":"僕はこれね無人島でコンピューター作れますよ","Speaker":null},{"Timestamp":"00:04:23","Token":"ゼロから","Speaker":null},{"Timestamp":"00:04:24","Token":"ただちょっと化学知識が足りないので","Speaker":null},{"Timestamp":"00:04:27","Token":"反動体が作れなくてつまづく可能性は","Speaker":null},{"Timestamp":"00:04:28","Token":"反動体一人じゃ作れなくなります","Speaker":null},{"Timestamp":"00:04:31","Token":"反動体メーカーがめっちゃ頑張って作ってるものでしょ","Speaker":null},{"Timestamp":"00:04:33","Token":"反動体は結局係素の組み合わせで","Speaker":null},{"Timestamp":"00:04:36","Token":"なんか蘇生を考えれば多分できるはずなんで","Speaker":null},{"Timestamp":"00:04:39","Token":"化学知識あって反動体作れるやつと僕がいれば","Speaker":null},{"Timestamp":"00:04:43","Token":"コンピューターがゼロから作れると思います","Speaker":null},{"Timestamp":"00:04:45","Token":"ドクターストーンみたいなことできるんだ","Speaker":null},{"Timestamp":"00:04:47","Token":"コンピューターをまず最初に作れるみたいな","Speaker":null},{"Timestamp":"00:04:48","Token":"そうなんですよ","Speaker":null},{"Timestamp":"00:04:49","Token":"ただ性能鬼悪いですから","Speaker":null},{"Timestamp":"00:04:53","Token":"同じものは作れます","Speaker":null},{"Timestamp":"00:04:55","Token":"理論は理解してるから","Speaker":null},{"Timestamp":"00:04:57","Token":"というね僕のこの無駄な知見","Speaker":null},{"Timestamp":"00:04:59","Token":"無駄じゃないよ","Speaker":null},{"Timestamp":"00:05:00","Token":"無駄な知見があるわけです","Speaker":null},{"Timestamp":"00:05:01","Token":"だって無人島行くことないからね","Speaker":null},{"Timestamp":"00:05:03","Token":"確かに","Speaker":null},{"Timestamp":"00:05:04","Token":"コンピューター作ることないから","Speaker":null},{"Timestamp":"00:05:05","Token":"これあんまり意味ないなと思ってたんですけど","Speaker":null},{"Timestamp":"00:05:08","Token":"せっかくこれ大学4年間で技能を習得したんで","Speaker":null},{"Timestamp":"00:05:12","Token":"大学の薄暗い地下のコンピュータルームに","Speaker":null},{"Timestamp":"00:05:16","Token":"閉じこもりながらせっかく習得したんです","Speaker":null},{"Timestamp":"00:05:19","Token":"何でか分からないですけど必ず地下にあるんですよね","Speaker":null},{"Timestamp":"00:05:21","Token":"へえ大学に地下があるんですか","Speaker":null},{"Timestamp":"00:05:24","Token":"大学のコンピュータルームってなぜか","Speaker":null},{"Timestamp":"00:05:26","Token":"大体地下にありがちっていうあるあるねだ","Speaker":null},{"Timestamp":"00:05:28","Token":"あるあるなんだそれ","Speaker":null},{"Timestamp":"00:05:29","Token":"あるあるねだ","Speaker":null},{"Timestamp":"00:05:30","Token":"電波悪そうなのに","Speaker":null},{"Timestamp":"00:05:31","Token":"ですね","Speaker":null},{"Timestamp":"00:05:32","Token":"電波とかそういうレベルじゃないんで","Speaker":null},{"Timestamp":"00:05:33","Token":"有線の太い大学語回線が繋がってるんで","Speaker":null},{"Timestamp":"00:05:38","Token":"ガチ税用のlinuxワークステーションは","Speaker":null},{"Timestamp":"00:05:42","Token":"地下に大体あるんです","Speaker":null},{"Timestamp":"00:05:43","Token":"へえなんか俺イメージ","Speaker":null},{"Timestamp":"00:05:44","Token":"今スパコンみたいなのに","Speaker":null},{"Timestamp":"00:05:45","Token":"イメージしとけばいいですか","Speaker":null},{"Timestamp":"00:05:47","Token":"すげえくだわーって出てるみたいな","Speaker":null},{"Timestamp":"00:05:49","Token":"そのイメージは途方もなく","Speaker":null},{"Timestamp":"00:05:50","Token":"間違ってるんですけど","Speaker":null},{"Timestamp":"00:05:52","Token":"出た出たオックスフォード","Speaker":null},{"Timestamp":"00:05:54","Token":"オックスフォードのやつね","Speaker":null},{"Timestamp":"00:05:56","Token":"途方もなく間違ってるんですけど","Speaker":null},{"Timestamp":"00:05:57","Token":"なんとなく地下ですごい設備があるんだな","Speaker":null},{"Timestamp":"00:06:00","Token":"って思っていただければよくて","Speaker":null},{"Timestamp":"00:06:02","Token":"そうなんですよ","Speaker":null},{"Timestamp":"00:06:03","Token":"うちのキャンパスもね","Speaker":null},{"Timestamp":"00:06:04","Token":"日の当たる明るいコンピュータルーム","Speaker":null},{"Timestamp":"00:06:06","Token":"あるんですよ","Speaker":null},{"Timestamp":"00:06:07","Token":"図書館とかに併設されてるよ","Speaker":null},{"Timestamp":"00:06:08","Token":"俺はそっちに行ってましたね","Speaker":null},{"Timestamp":"00:06:09","Token":"それはでもWindows使うやつでしょ","Speaker":null},{"Timestamp":"00:06:12","Token":"そうそうそう","Speaker":null},{"Timestamp":"00:06:13","Token":"非ガチ税用の","Speaker":null},{"Timestamp":"00:06:14","Token":"そうなの","Speaker":null},{"Timestamp":"00:06:15","Token":"日が当たるコンピュータルームなんでそこは","Speaker":null},{"Timestamp":"00:06:17","Token":"ガチ税用のLinuxワークステーションっていうね","Speaker":null},{"Timestamp":"00:06:19","Token":"黒い画面に白い文字しか出ない","Speaker":null},{"Timestamp":"00:06:21","Token":"OSを使うんで","Speaker":null},{"Timestamp":"00:06:24","Token":"気がおかしくなりそうですね","Speaker":null},{"Timestamp":"00:06:25","Token":"それの人たちのための地下の","Speaker":null},{"Timestamp":"00:06:26","Token":"薄暗い部屋に与えられてましたね","Speaker":null},{"Timestamp":"00:06:28","Token":"あれですね","Speaker":null},{"Timestamp":"00:06:29","Token":"一般の人たちとは接せない場所にいるんです","Speaker":null},{"Timestamp":"00:06:32","Token":"そうですよ","Speaker":null},{"Timestamp":"00:06:34","Token":"黒い画面しか出てこないから","Speaker":null},{"Timestamp":"00:06:36","Token":"動揺するしかない","Speaker":null},{"Timestamp":"00:06:37","Token":"そんなカードの設定なんだ","Speaker":null},{"Timestamp":"00:06:40","Token":"そうそうそう","Speaker":null},{"Timestamp":"00:06:41","Token":"そこにせっかく4年間閉じこもってたんでね","Speaker":null},{"Timestamp":"00:06:43","Token":"その知見を今日は皆さんにお伝えしていこうと思います","Speaker":null},{"Timestamp":"00:06:46","Token":"よろしくお願いします","Speaker":null},{"Timestamp":"00:06:49","Token":"まず問題です","Speaker":null},{"Timestamp":"00:06:53","Token":"13たす25は?","Speaker":null},{"Timestamp":"00:06:55","Token":"え38","Speaker":null},{"Timestamp":"00:06:56","Token":"おー素晴らしい","Speaker":null},{"Timestamp":"00:06:58","Token":"よくできますね","Speaker":null},{"Timestamp":"00:06:59","Token":"これ小学生でしょ","Speaker":null},{"Timestamp":"00:07:00","Token":"いやこれみずのさんね","Speaker":null},{"Timestamp":"00:07:01","Token":"今日からコンピュータ名乗れますね","Speaker":null},{"Timestamp":"00:07:04","Token":"名乗れねえ","Speaker":null},{"Timestamp":"00:07:06","Token":"名乗れるか","Speaker":null},{"Timestamp":"00:07:07","Token":"だってね5元オタクですよねあなた","Speaker":null},{"Timestamp":"00:07:10","Token":"コンピュータってどういう5元","Speaker":null},{"Timestamp":"00:07:12","Token":"5元というか単語のつもりですか","Speaker":null},{"Timestamp":"00:07:13","Token":"コンピュートをプラスERですよね","Speaker":null},{"Timestamp":"00:07:15","Token":"コンピュートを計算するとか考えるみたいな意味だったはずなので","Speaker":null},{"Timestamp":"00:07:18","Token":"素晴らしいその通りです","Speaker":null},{"Timestamp":"00:07:19","Token":"だから計算するものなんですよ","Speaker":null},{"Timestamp":"00:07:22","Token":"コンピュータって","Speaker":null},{"Timestamp":"00:07:24","Token":"めっちゃ余談なんですけど","Speaker":null},{"Timestamp":"00:07:25","Token":"昔NASAの全身の団体とかには","Speaker":null},{"Timestamp":"00:07:28","Token":"コンピュータという仕事の人いたらしいです","Speaker":null},{"Timestamp":"00:07:31","Token":"計算者","Speaker":null},{"Timestamp":"00:07:32","Token":"そう計算者","Speaker":null},{"Timestamp":"00:07:33","Token":"へー","Speaker":null},{"Timestamp":"00:07:35","Token":"めちゃくちゃ天体の運行とか複雑な計算なんで","Speaker":null},{"Timestamp":"00:07:39","Token":"それをひたすらガリガリやるだけの職種の人","Speaker":null},{"Timestamp":"00:07:41","Token":"かっこいい","Speaker":null},{"Timestamp":"00:07:43","Token":"なんでコンピュータって計算する人なんですよ","Speaker":null},{"Timestamp":"00:07:45","Token":"俺ずっとそれ思ってたんですよ","Speaker":null},{"Timestamp":"00:07:47","Token":"役語悪すぎるだろって","Speaker":null},{"Timestamp":"00:07:49","Token":"電卓と一緒じゃんじゃあっていう","Speaker":null},{"Timestamp":"00:07:51","Token":"そうですよ","Speaker":null},{"Timestamp":"00:07:52","Token":"いやそうじゃないよ","Speaker":null},{"Timestamp":"00:07:54","Token":"コンピュータと電卓は違うよ","Speaker":null},{"Timestamp":"00:07:56","Token":"いやいや一緒ですよ","Speaker":null},{"Timestamp":"00:07:57","Token":"いや一緒じゃねえって","Speaker":null},{"Timestamp":"00:07:59","Token":"ということが並行性に必ずなる","Speaker":null},{"Timestamp":"00:08:01","Token":"これなぜならみずのさんは魔法の箱だと思ってるから","Speaker":null},{"Timestamp":"00:08:04","Token":"高度な電卓としても","Speaker":null},{"Timestamp":"00:08:06","Token":"すごい差あると思うけどっていう感じですよね","Speaker":null},{"Timestamp":"00:08:09","Token":"そうなんですよ計算機じゃないじゃんって","Speaker":null},{"Timestamp":"00:08:10","Token":"みんな思ってるんだけど","Speaker":null},{"Timestamp":"00:08:12","Token":"いや計算機なのよっていう","Speaker":null},{"Timestamp":"00:08:14","Token":"今日魔法の箱から脱却して計算機だと思ってもらうための","Speaker":null},{"Timestamp":"00:08:18","Token":"第一回ですこれは","Speaker":null},{"Timestamp":"00:08:19","Token":"ちょっとそれについて足しておきてもいいですか","Speaker":null},{"Timestamp":"00:08:22","Token":"落合陽一さんっていうメディアーティスト","Speaker":null},{"Timestamp":"00:08:25","Token":"津久保大学の","Speaker":null},{"Timestamp":"00:08:26","Token":"がデジタルネイチャーっていう概念を提唱して","Speaker":null},{"Timestamp":"00:08:30","Token":"落合さんが提唱してるっていうよりは","Speaker":null},{"Timestamp":"00:08:32","Token":"落合さんが日本で割とその言説をやってるんですけど","Speaker":null},{"Timestamp":"00:08:36","Token":"それも計算機自然とかっていうふうに","Speaker":null},{"Timestamp":"00:08:39","Token":"落合さん訳すし","Speaker":null},{"Timestamp":"00:08:40","Token":"あんまりコンピュータって言わないんですよね","Speaker":null},{"Timestamp":"00:08:41","Token":"落合さん著書の中とかで","Speaker":null},{"Timestamp":"00:08:43","Token":"そうだ計算機って言ってるイメージある","Speaker":null},{"Timestamp":"00:08:44","Token":"特にプラネッツから出てる魔法の聖記とか","Speaker":null},{"Timestamp":"00:08:47","Token":"デジタルネイチャーみたいな多少ちょっと","Speaker":null},{"Timestamp":"00:08:49","Token":"多分ハイブローな人向けの","Speaker":null},{"Timestamp":"00:08:52","Token":"ちょっと難しい本とかだと必ず計算機って言ってて","Speaker":null},{"Timestamp":"00:08:55","Token":"これ訳語わかんない人絶対困るだろうなって","Speaker":null},{"Timestamp":"00:08:57","Token":"いつも思ってたんですよ読んでて","Speaker":null},{"Timestamp":"00:08:59","Token":"確かにね計算機って言われてみんな電卓のイメージ","Speaker":null},{"Timestamp":"00:09:01","Token":"そうそうだから本のタイトルに","Speaker":null},{"Timestamp":"00:09:03","Token":"計算機自然とか書いてあったりすると","Speaker":null},{"Timestamp":"00:09:05","Token":"書いてあったか覚えてないけど","Speaker":null},{"Timestamp":"00:09:07","Token":"僕みたいな僕でさらにコンピュータの","Speaker":null},{"Timestamp":"00:09:09","Token":"語源知らない人からすると","Speaker":null},{"Timestamp":"00:09:11","Token":"計算機の話なんで出てくんのって","Speaker":null},{"Timestamp":"00:09:13","Token":"絶対なったと思うんですよ","Speaker":null},{"Timestamp":"00:09:15","Token":"じゃあもう今日まさに落合良一さんの本で","Speaker":null},{"Timestamp":"00:09:17","Token":"パニックになった人のための救済の回になります","Speaker":null},{"Timestamp":"00:09:21","Token":"ただ落合さんはコンピュータによって","Speaker":null},{"Timestamp":"00:09:23","Token":"魔法の聖記になるっていうこと言ってるから","Speaker":null},{"Timestamp":"00:09:25","Token":"コンピュータによって魔法がっていう","Speaker":null},{"Timestamp":"00:09:27","Token":"多分論理関係になってたはずですけど","Speaker":null},{"Timestamp":"00:09:29","Token":"そうですねでもねだから両立します","Speaker":null},{"Timestamp":"00:09:32","Token":"今日皆さんにはコンピュータは","Speaker":null},{"Timestamp":"00:09:34","Token":"魔法の箱じゃないということを","Speaker":null},{"Timestamp":"00:09:36","Token":"分かっていただいた上で","Speaker":null},{"Timestamp":"00:09:37","Token":"なんで魔法に見えるのかみたいな","Speaker":null},{"Timestamp":"00:09:39","Token":"魔法じゃんっていう話をします","Speaker":null},{"Timestamp":"00:09:41","Token":"お楽しみ","Speaker":null},{"Timestamp":"00:09:45","Token":"水野さん13たす25計算できたんで","Speaker":null},{"Timestamp":"00:09:47","Token":"コンピュータだと思うんですよ","Speaker":null},{"Timestamp":"00:09:49","Token":"まあいいよコンピュータで俺","Speaker":null},{"Timestamp":"00:09:52","Token":"明日から飲み会とかでコンピュータです","Speaker":null},{"Timestamp":"00:09:56","Token":"どうしたの","Speaker":null},{"Timestamp":"00:09:57","Token":"計算できるんで計算する人なんで","Speaker":null},{"Timestamp":"00:09:59","Token":"そうですね","Speaker":null},{"Timestamp":"00:10:00","Token":"本当に魔法に見えてると思うんですけど","Speaker":null},{"Timestamp":"00:10:03","Token":"コンピュータやってることって","Speaker":null},{"Timestamp":"00:10:05","Token":"本当にこのレベルなんですよ","Speaker":null},{"Timestamp":"00:10:07","Token":"13たす25計算するとか","Speaker":null},{"Timestamp":"00:10:10","Token":"もしくはこっちに書いてあるものを","Speaker":null},{"Timestamp":"00:10:11","Token":"こっちに書き写すとか","Speaker":null},{"Timestamp":"00:10:13","Token":"あとあっちから来たものを","Speaker":null},{"Timestamp":"00:10:15","Token":"こっちに書き写すとか","Speaker":null},{"Timestamp":"00:10:17","Token":"そのレベルのことしかやってないんですよ","Speaker":null},{"Timestamp":"00:10:18","Token":"コンピュータは","Speaker":null},{"Timestamp":"00:10:19","Token":"いやそれは嘘でしょ","Speaker":null},{"Timestamp":"00:10:22","Token":"マジマジ","Speaker":null},{"Timestamp":"00:10:23","Token":"マジなのよ","Speaker":null},{"Timestamp":"00:10:24","Token":"でも水野さんに","Speaker":null},{"Timestamp":"00:10:27","Token":"ここで一つの問題が生じるんですよ","Speaker":null},{"Timestamp":"00:10:30","Token":"今僕が言ったようなレベルのこと","Speaker":null},{"Timestamp":"00:10:31","Token":"全部できるじゃないですか","Speaker":null},{"Timestamp":"00:10:32","Token":"水野さんも","Speaker":null},{"Timestamp":"00:10:34","Token":"書き写すとかね","Speaker":null},{"Timestamp":"00:10:35","Token":"計算するとかね","Speaker":null},{"Timestamp":"00:10:36","Token":"だったらこれもできて叱るべきなんですけど","Speaker":null},{"Timestamp":"00:10:39","Token":"OK水野","Speaker":null},{"Timestamp":"00:10:40","Token":"ゆる言語予約ラジオを流して","Speaker":null},{"Timestamp":"00:10:42","Token":"はいということで始まりました","Speaker":null},{"Timestamp":"00:10:46","Token":"YouTubeとかフォトゲスト","Speaker":null},{"Timestamp":"00:10:48","Token":"再生できるべきなんですよ","Speaker":null},{"Timestamp":"00:10:51","Token":"そうじゃないですか","Speaker":null},{"Timestamp":"00:10:52","Token":"だって僕の主張は","Speaker":null},{"Timestamp":"00:10:53","Token":"コンピュータのやってることって","Speaker":null},{"Timestamp":"00:10:54","Token":"一個一個13たす25とか","Speaker":null},{"Timestamp":"00:10:57","Token":"書き写すとかしかやってない","Speaker":null},{"Timestamp":"00:10:59","Token":"それ水野さんできるわけじゃないですか","Speaker":null},{"Timestamp":"00:11:01","Token":"だったら","Speaker":null},{"Timestamp":"00:11:03","Token":"論理の秘訳すんのやめて","Speaker":null},{"Timestamp":"00:11:05","Token":"いやいやそうでしょ","Speaker":null},{"Timestamp":"00:11:06","Token":"そういうことで同じ動作できる","Speaker":null},{"Timestamp":"00:11:08","Token":"メモリーに入ってないから","Speaker":null},{"Timestamp":"00:11:10","Token":"うん","Speaker":null},{"Timestamp":"00:11:12","Token":"ハードウェア的な部分はあると思います","Speaker":null},{"Timestamp":"00:11:14","Token":"だからインターネット回線","Speaker":null},{"Timestamp":"00:11:15","Token":"今こういうこと言うと","Speaker":null},{"Timestamp":"00:11:16","Token":"Wi-Fiを受信する部分がついてないから","Speaker":null},{"Timestamp":"00:11:19","Token":"できないっていうのはあるんですけど","Speaker":null},{"Timestamp":"00:11:20","Token":"それは全然ただの信号なんで","Speaker":null},{"Timestamp":"00:11:23","Token":"言うたら","Speaker":null},{"Timestamp":"00:11:25","Token":"Wi-Fiの波","Speaker":null},{"Timestamp":"00:11:26","Token":"それで原理的には同じ受信ができるので","Speaker":null},{"Timestamp":"00:11:30","Token":"コマック","Speaker":null},{"Timestamp":"00:11:31","Token":"コマックとか別になんでもいいですよ","Speaker":null},{"Timestamp":"00:11:32","Token":"脳波でもいいし","Speaker":null},{"Timestamp":"00:11:33","Token":"なんかで受信すればいいわけで","Speaker":null},{"Timestamp":"00:11:35","Token":"要するにその情報","Speaker":null},{"Timestamp":"00:11:37","Token":"例えばだから僕の脳みそにUSBさせて","Speaker":null},{"Timestamp":"00:11:39","Token":"そこにユルゲンウォークラジオの","Speaker":null},{"Timestamp":"00:11:41","Token":"そのなんか例えば","Speaker":null},{"Timestamp":"00:11:42","Token":"素材を入れてたら出せるよねって言ってる","Speaker":null},{"Timestamp":"00:11:44","Token":"そうそうそう","Speaker":null},{"Timestamp":"00:11:45","Token":"再生はできておかしくないでしょ","Speaker":null},{"Timestamp":"00:11:47","Token":"っていう話ですもんね","Speaker":null},{"Timestamp":"00:11:49","Token":"意味はわかりますね","Speaker":null},{"Timestamp":"00:11:50","Token":"今の指示の内容と","Speaker":null},{"Timestamp":"00:11:52","Token":"何を求めてるかはわかりましたね","Speaker":null},{"Timestamp":"00:11:53","Token":"でもじゃあそれでできます?","Speaker":null},{"Timestamp":"00:11:55","Token":"Wi-Fi受信機能を","Speaker":null},{"Timestamp":"00:11:56","Token":"みずのの脳につけたとして","Speaker":null},{"Timestamp":"00:11:57","Token":"USB挿す機能をつけたとして","Speaker":null},{"Timestamp":"00:11:59","Token":"再生できると思います","Speaker":null},{"Timestamp":"00:12:01","Token":"いや家庭がちょっと","Speaker":null},{"Timestamp":"00:12:04","Token":"すごいな","Speaker":null},{"Timestamp":"00:12:07","Token":"怖すぎるよそんなの","Speaker":null},{"Timestamp":"00:12:09","Token":"でも最近結構研究領域でもありますからね","Speaker":null},{"Timestamp":"00:12:11","Token":"脳波直接脳に電流流して","Speaker":null},{"Timestamp":"00:12:13","Token":"人間を動かすみたいな","Speaker":null},{"Timestamp":"00:12:15","Token":"研究領域あるんで","Speaker":null},{"Timestamp":"00:12:17","Token":"今のもう少し","Speaker":null},{"Timestamp":"00:12:18","Token":"もう少し馴染みのある風に直すと","Speaker":null},{"Timestamp":"00:12:20","Token":"例えば演習率を言ってって言われた時に","Speaker":null},{"Timestamp":"00:12:23","Token":"演習率を100桁もし覚えてたら出せる","Speaker":null},{"Timestamp":"00:12:25","Token":"その指示に対して演習率100桁言えるか","Speaker":null},{"Timestamp":"00:12:27","Token":"っていう感じでしょ","Speaker":null},{"Timestamp":"00:12:28","Token":"そうそうそう","Speaker":null},{"Timestamp":"00:12:29","Token":"それはできるんじゃないですか","Speaker":null},{"Timestamp":"00:12:30","Token":"できりますよそれは","Speaker":null},{"Timestamp":"00:12:31","Token":"でもじゃあPodcastの再生ってできそうですか","Speaker":null},{"Timestamp":"00:12:33","Token":"だから外付けメモリーがないと","Speaker":null},{"Timestamp":"00:12:35","Token":"こんな感じですかね","Speaker":null},{"Timestamp":"00:12:37","Token":"これは断言できるんですけど","Speaker":null},{"Timestamp":"00:12:38","Token":"外付けメモリーがあっても無理です","Speaker":null},{"Timestamp":"00:12:41","Token":"ああそうなの","Speaker":null},{"Timestamp":"00:12:43","Token":"そうなんですよ","Speaker":null},{"Timestamp":"00:12:44","Token":"だからそれって話おかしいよね","Speaker":null},{"Timestamp":"00:12:46","Token":"っていうことですね","Speaker":null},{"Timestamp":"00:12:47","Token":"一つ一つのさっき言った動作はできる","Speaker":null},{"Timestamp":"00:12:50","Token":"計算はできるわけで","Speaker":null},{"Timestamp":"00:12:52","Token":"でハードウェア的に","Speaker":null},{"Timestamp":"00:12:53","Token":"それをPodcastを受信する機能が","Speaker":null},{"Timestamp":"00:12:55","Token":"Mizunoについてだとしても","Speaker":null},{"Timestamp":"00:12:57","Token":"すれば言えてもおかしくないじゃないですか","Speaker":null},{"Timestamp":"00:13:00","Token":"再生できてもおかしくない","Speaker":null},{"Timestamp":"00:13:01","Token":"ここで言う言うってのは","Speaker":null},{"Timestamp":"00:13:02","Token":"Podcastの音源通りの声を","Speaker":null},{"Timestamp":"00:13:04","Token":"全く同じように発するってこと","Speaker":null},{"Timestamp":"00:13:06","Token":"それは無理だね","Speaker":null},{"Timestamp":"00:13:07","Token":"まあまあまあまあいいや","Speaker":null},{"Timestamp":"00:13:09","Token":"ソランジルじゃなくてもいいですよね","Speaker":null},{"Timestamp":"00:13:11","Token":"そうでもねソランジルでもいい","Speaker":null},{"Timestamp":"00:13:13","Token":"もうねこの話長いわ","Speaker":null},{"Timestamp":"00:13:15","Token":"ごめんちょっと例えが複雑すぎて","Speaker":null},{"Timestamp":"00:13:17","Token":"ハードウェア的な部分は今置いといてよくて","Speaker":null},{"Timestamp":"00:13:20","Token":"再生ができるかどうかって話なんだけど","Speaker":null},{"Timestamp":"00:13:22","Token":"難しい話になってしまう","Speaker":null},{"Timestamp":"00:13:23","Token":"死を末設にとられてしまった","Speaker":null},{"Timestamp":"00:13:25","Token":"ちょっとねもう大丈夫です","Speaker":null},{"Timestamp":"00:13:27","Token":"まあでも皆さんに思っていて欲しいのは","Speaker":null},{"Timestamp":"00:13:29","Token":"Hey Mizuno","Speaker":null},{"Timestamp":"00:13:31","Token":"OK Mizunoかな","Speaker":null},{"Timestamp":"00:13:32","Token":"OK Mizuno再生してって言われても","Speaker":null},{"Timestamp":"00:13:33","Token":"再生できなさそうだよね","Speaker":null},{"Timestamp":"00:13:35","Token":"同じシンプルな動作で","Speaker":null},{"Timestamp":"00:13:37","Token":"それはできるんだとしたら","Speaker":null},{"Timestamp":"00:13:38","Token":"できてもおかしくないでしょ","Speaker":null},{"Timestamp":"00:13:40","Token":"なぜできないのかなっていう問いだけ","Speaker":null},{"Timestamp":"00:13:42","Token":"とりあえず頭に置いておいても","Speaker":null},{"Timestamp":"00:13:43","Token":"要素還元主義的なアプローチができないと","Speaker":null},{"Timestamp":"00:13:46","Token":"そうですね","Speaker":null},{"Timestamp":"00:13:47","Token":"だからみんながこの悩み抱えて","Speaker":null},{"Timestamp":"00:13:49","Token":"生きてないの僕おかしいなと思うんですけど","Speaker":null},{"Timestamp":"00:13:51","Token":"どの悩みですか","Speaker":null},{"Timestamp":"00:13:52","Token":"なんで俺はポッドキャストが再生できないんだ","Speaker":null},{"Timestamp":"00:13:55","Token":"いや","Speaker":null},{"Timestamp":"00:13:58","Token":"こうやって俺も聞かれてるんですかね","Speaker":null},{"Timestamp":"00:13:59","Token":"変なところに課題意識燃やしたときに","Speaker":null},{"Timestamp":"00:14:02","Token":"こんな感じの気持ちになってんのか","Speaker":null},{"Timestamp":"00:14:04","Token":"そうそうそう","Speaker":null},{"Timestamp":"00:14:05","Token":"ブッシュこれで立功した方がいいみたいな","Speaker":null},{"Timestamp":"00:14:07","Token":"はいはい","Speaker":null},{"Timestamp":"00:14:08","Token":"いやなんか","Speaker":null},{"Timestamp":"00:14:09","Token":"何言ってんだろうなと思ってんですけど","Speaker":null},{"Timestamp":"00:14:11","Token":"こんな感じなんだ","Speaker":null},{"Timestamp":"00:14:12","Token":"こんな感じです","Speaker":null},{"Timestamp":"00:14:13","Token":"なぜ俺はYouTubeが再生できないんだって","Speaker":null},{"Timestamp":"00:14:15","Token":"悩んだ方がいいっていう主張と一緒ですよあれ","Speaker":null},{"Timestamp":"00:14:17","Token":"本当に一緒か","Speaker":null},{"Timestamp":"00:14:18","Token":"俺まだ疑わしいから","Speaker":null},{"Timestamp":"00:14:20","Token":"ちょっと聞いてる人に聞きたいですね","Speaker":null},{"Timestamp":"00:14:21","Token":"ごめんそうだね","Speaker":null},{"Timestamp":"00:14:22","Token":"コメント欄でちょっと全然違うよそれは","Speaker":null},{"Timestamp":"00:14:24","Token":"と言われる可能性はありますけど","Speaker":null},{"Timestamp":"00:14:26","Token":"みんな悩んで生きてない","Speaker":null},{"Timestamp":"00:14:27","Token":"僕は悩まないんですよ","Speaker":null},{"Timestamp":"00:14:28","Token":"なんでなら僕は知ってるからその理由を","Speaker":null},{"Timestamp":"00:14:30","Token":"はい","Speaker":null},{"Timestamp":"00:14:33","Token":"うんうん","Speaker":null},{"Timestamp":"00:14:36","Token":"だから皆さんの知ってる知識の理屈でいくと","Speaker":null},{"Timestamp":"00:14:41","Token":"計算が簡単にできることと","Speaker":null},{"Timestamp":"00:14:43","Token":"そうするとYouTubeとか再生できるはずだよね","Speaker":null},{"Timestamp":"00:14:46","Token":"ってことに推論としてはなっていて","Speaker":null},{"Timestamp":"00:14:47","Token":"なおにこいつらはこの無事を抱えたまま生きてるな","Speaker":null},{"Timestamp":"00:14:49","Token":"そうそうそう","Speaker":null},{"Timestamp":"00:14:51","Token":"いや考えたことないよ","Speaker":null},{"Timestamp":"00:14:53","Token":"みんな悩んだほうがいいなと思いながら","Speaker":null},{"Timestamp":"00:14:54","Token":"いっぱい生きてるんですけど","Speaker":null},{"Timestamp":"00:14:56","Token":"じゃあ結論から言いますね","Speaker":null},{"Timestamp":"00:14:58","Token":"はい","Speaker":null},{"Timestamp":"00:15:02","Token":"YouTubeの再生はできないのか","Speaker":null},{"Timestamp":"00:15:05","Token":"結論から言うと量が違うからなんですよ","Speaker":null},{"Timestamp":"00:15:08","Token":"えそうなの","Speaker":null},{"Timestamp":"00:15:09","Token":"単に質的な差だとみんな思ってるんですけど","Speaker":null},{"Timestamp":"00:15:12","Token":"量的な差にすぎないんですよ","Speaker":null},{"Timestamp":"00:15:14","Token":"計算がめっちゃこなせるとできるってこと","Speaker":null},{"Timestamp":"00:15:16","Token":"ということです","Speaker":null},{"Timestamp":"00:15:17","Token":"計算の量が違うからYouTube再生できないですよ我々は","Speaker":null},{"Timestamp":"00:15:20","Token":"そうなの","Speaker":null},{"Timestamp":"00:15:21","Token":"そうなの","Speaker":null},{"Timestamp":"00:15:22","Token":"結局計算になるんで","Speaker":null},{"Timestamp":"00:15:23","Token":"へー","Speaker":null},{"Timestamp":"00:15:25","Token":"全然質的には一緒です","Speaker":null},{"Timestamp":"00:15:27","Token":"13たす25計算するのと","Speaker":null},{"Timestamp":"00:15:29","Token":"俺めっちゃ算数めっちゃ頑張って","Speaker":null},{"Timestamp":"00:15:31","Token":"記憶力もすげー鍛えたら","Speaker":null},{"Timestamp":"00:15:33","Token":"ワンチャンできるようになるかもしれない","Speaker":null},{"Timestamp":"00:15:35","Token":"YouTube再生できるようになるかもしれないんですけど","Speaker":null},{"Timestamp":"00:15:37","Token":"そのために必要な計算回数を","Speaker":null},{"Timestamp":"00:15:39","Token":"ちょっとざっくりお伝えしますね","Speaker":null},{"Timestamp":"00:15:42","Token":"どれぐらいだろう","Speaker":null},{"Timestamp":"00:15:43","Token":"13たす25みたいなレベルの計算って","Speaker":null},{"Timestamp":"00:15:45","Token":"みずのさん1秒に何個できます","Speaker":null},{"Timestamp":"00:15:47","Token":"1個とか2個じゃなく","Speaker":null},{"Timestamp":"00:15:49","Token":"1秒に1個さばけたらいいぐらいじゃないですか","Speaker":null},{"Timestamp":"00:15:51","Token":"1秒に1個","Speaker":null},{"Timestamp":"00:15:53","Token":"そうですね計算早ければ","Speaker":null},{"Timestamp":"00:15:54","Token":"2個でいけるかもしれないですね","Speaker":null},{"Timestamp":"00:15:57","Token":"YouTube再生したいみたいな","Speaker":null},{"Timestamp":"00:15:59","Token":"今の我々が持ってるスマホ","Speaker":null},{"Timestamp":"00:16:01","Token":"1秒に何回計算してるかというと","Speaker":null},{"Timestamp":"00:16:03","Token":"何回だと思いますか","Speaker":null},{"Timestamp":"00:16:05","Token":"結構でもやっぱスマートフォンぐらいだとすごそうですね","Speaker":null},{"Timestamp":"00:16:08","Token":"やっぱわかんない","Speaker":null},{"Timestamp":"00:16:09","Token":"ちょっと大きめに見積もりますよ","Speaker":null},{"Timestamp":"00:16:11","Token":"100ぐらいいってんじゃないですか","Speaker":null},{"Timestamp":"00:16:12","Token":"20億です","Speaker":null},{"Timestamp":"00:16:17","Token":"途方もなく間違った","Speaker":null},{"Timestamp":"00:16:18","Token":"途方もなく間違ってますね","Speaker":null},{"Timestamp":"00:16:20","Token":"全然見積もりできない","Speaker":null},{"Timestamp":"00:16:21","Token":"1秒間に20億回ぐらい計算してると","Speaker":null},{"Timestamp":"00:16:24","Token":"思ってもらってない","Speaker":null},{"Timestamp":"00:16:26","Token":"日本の人口の人全員集めて","Speaker":null},{"Timestamp":"00:16:28","Token":"スマホと計算バトルしても勝てない","Speaker":null},{"Timestamp":"00:16:30","Token":"そうなんですよ","Speaker":null},{"Timestamp":"00:16:31","Token":"足し算で国民全員かかっても","Speaker":null},{"Timestamp":"00:16:34","Token":"全然1台のスマホにボロ負けします","Speaker":null},{"Timestamp":"00:16:37","Token":"わすげえ","Speaker":null},{"Timestamp":"00:16:38","Token":"そうなんですよ","Speaker":null},{"Timestamp":"00:16:39","Token":"その異常な計算能力を持った","Speaker":null},{"Timestamp":"00:16:41","Token":"よくわからないものをよくもこんな上手く利用できてますね","Speaker":null},{"Timestamp":"00:16:44","Token":"そうなのよ","Speaker":null},{"Timestamp":"00:16:45","Token":"そこもね","Speaker":null},{"Timestamp":"00:16:46","Token":"それはね第2回でやります","Speaker":null},{"Timestamp":"00:16:47","Token":"それ利用できてるのすごくない","Speaker":null},{"Timestamp":"00:16:49","Token":"それ","Speaker":null},{"Timestamp":"00:16:50","Token":"だって国民全員より上回った計算能力を持ってるやつ","Speaker":null},{"Timestamp":"00:16:53","Token":"我々はちゃんと利用できてる","Speaker":null},{"Timestamp":"00:16:55","Token":"ね例えばですけど","Speaker":null},{"Timestamp":"00:16:56","Token":"SAPIERみたいなちょっと前に公開された","Speaker":null},{"Timestamp":"00:16:58","Token":"いろんな言語が操れる人って","Speaker":null},{"Timestamp":"00:17:00","Token":"言語学者とかにいるんですけど","Speaker":null},{"Timestamp":"00:17:02","Token":"それがそのYouTube再生するみたいな能力に","Speaker":null},{"Timestamp":"00:17:05","Token":"生きてこないですもんねなかなか","Speaker":null},{"Timestamp":"00:17:06","Token":"そうですね","Speaker":null},{"Timestamp":"00:17:07","Token":"そうそうそう","Speaker":null},{"Timestamp":"00:17:09","Token":"そんなYouTube再生するみたいなことに生きてくるのすごいですね","Speaker":null},{"Timestamp":"00:17:12","Token":"そうなんですよ","Speaker":null},{"Timestamp":"00:17:13","Token":"ね","Speaker":null},{"Timestamp":"00:17:14","Token":"ちなみにこの20億回ですみたいなことをサクッと言ったんですけど","Speaker":null},{"Timestamp":"00:17:17","Token":"何かっていうと","Speaker":null},{"Timestamp":"00:17:18","Token":"皆さんも絶対この数字見たことあって","Speaker":null},{"Timestamp":"00:17:20","Token":"はい","Speaker":null},{"Timestamp":"00:17:21","Token":"スマホのスペック表って見たことないですか","Speaker":null},{"Timestamp":"00:17:24","Token":"え","Speaker":null},{"Timestamp":"00:17:27","Token":"いやいやだからそのiPhone12のカタログとか見ると","Speaker":null},{"Timestamp":"00:17:31","Token":"だいたい書いてあるでしょ","Speaker":null},{"Timestamp":"00:17:35","Token":"そんな興味持たないでしょ","Speaker":null},{"Timestamp":"00:17:37","Token":"出たーそれのやつ","Speaker":null},{"Timestamp":"00:17:39","Token":"じゃあどうやってスマホ買うのみんな","Speaker":null},{"Timestamp":"00:17:40","Token":"え","Speaker":null},{"Timestamp":"00:17:41","Token":"そんななんか記事とか見て","Speaker":null},{"Timestamp":"00:17:44","Token":"誰かが勧めてるもの買えばいいじゃん","Speaker":null},{"Timestamp":"00:17:46","Token":"えみずほんさん自分の持ってるiPhoneの容量を","Speaker":null},{"Timestamp":"00:17:48","Token":"何GBとか知ってますか","Speaker":null},{"Timestamp":"00:17:49","Token":"あー怪しいね","Speaker":null},{"Timestamp":"00:17:51","Token":"いやそれも知らないんだよ","Speaker":null},{"Timestamp":"00:17:52","Token":"32か64か","Speaker":null},{"Timestamp":"00:17:53","Token":"すご","Speaker":null},{"Timestamp":"00:17:54","Token":"でももうそのなんかあの","Speaker":null},{"Timestamp":"00:17:56","Token":"他のストレージに移せるから","Speaker":null},{"Timestamp":"00:17:57","Token":"はいはいはい","Speaker":null},{"Timestamp":"00:17:58","Token":"実はどうでもいいですね","Speaker":null},{"Timestamp":"00:17:59","Token":"すご","Speaker":null},{"Timestamp":"00:18:00","Token":"そんなんてことはそれ僕にとってはビビリ状態で","Speaker":null},{"Timestamp":"00:18:04","Token":"俺今煽られてんの?俺","Speaker":null},{"Timestamp":"00:18:06","Token":"いやだってねその","Speaker":null},{"Timestamp":"00:18:08","Token":"スマホのスペックって全てなわけですよ","Speaker":null},{"Timestamp":"00:18:11","Token":"そいつが何ができるかは全てが書いてあるわけで","Speaker":null},{"Timestamp":"00:18:13","Token":"不動産に例えると","Speaker":null},{"Timestamp":"00:18:15","Token":"風呂トイレ別とか広さとか","Speaker":null},{"Timestamp":"00:18:18","Token":"そういうことが書いてあるわけですよ","Speaker":null},{"Timestamp":"00:18:19","Token":"スマホのスペックとか","Speaker":null},{"Timestamp":"00:18:21","Token":"風呂とかトイレとかアプリみたいなもんでしょ","Speaker":null},{"Timestamp":"00:18:24","Token":"いや違う違う","Speaker":null},{"Timestamp":"00:18:25","Token":"動かせないからスマホのスペック部分は","Speaker":null},{"Timestamp":"00:18:27","Token":"アプリは家具ですよ","Speaker":null},{"Timestamp":"00:18:29","Token":"タンスとか冷蔵庫とかは買ってこれるけど","Speaker":null},{"Timestamp":"00:18:31","Token":"風呂とかは買えないじゃん","Speaker":null},{"Timestamp":"00:18:32","Token":"でもその不便感じたことないよ別に","Speaker":null},{"Timestamp":"00:18:35","Token":"スペックをやべぇスペック見落としたせいで","Speaker":null},{"Timestamp":"00:18:37","Token":"これできないやって言って","Speaker":null},{"Timestamp":"00:18:38","Token":"困った覚えがないけど","Speaker":null},{"Timestamp":"00:18:40","Token":"そうか僕はちょっとミスって","Speaker":null},{"Timestamp":"00:18:43","Token":"しょっちゅう苦悩してるんですけど","Speaker":null},{"Timestamp":"00:18:44","Token":"大変ですね","Speaker":null},{"Timestamp":"00:18:45","Token":"メモリ上げとけばよかったもうちょっととか","Speaker":null},{"Timestamp":"00:18:47","Token":"グラフをもう一個いいやつにしとけばよかったとかね","Speaker":null},{"Timestamp":"00:18:49","Token":"よくあるんですけどパソコン買った後","Speaker":null},{"Timestamp":"00:18:50","Token":"知恵の悲しみですね","Speaker":null},{"Timestamp":"00:18:53","Token":"ありましたね知恵の悲しみ","Speaker":null},{"Timestamp":"00:18:54","Token":"何ていうのロシアのか何かの義極でしたっけ","Speaker":null},{"Timestamp":"00:18:56","Token":"そう義極そうですね","Speaker":null},{"Timestamp":"00:18:58","Token":"義極のタイトルだっけ","Speaker":null},{"Timestamp":"00:18:59","Token":"知恵の悲しみ","Speaker":null},{"Timestamp":"00:19:00","Token":"いろいろなことを知った結果","Speaker":null},{"Timestamp":"00:19:03","Token":"逆に不幸になることみたいな感じでしたよね","Speaker":null},{"Timestamp":"00:19:04","Token":"そうですね義極ベースで生まれた勧誘屋ですね","Speaker":null},{"Timestamp":"00:19:08","Token":"もう全然悩んだことないから俺は","Speaker":null},{"Timestamp":"00:19:11","Token":"僕はねあのとかわかる人は","Speaker":null},{"Timestamp":"00:19:13","Token":"コンピュータースマホ買うとき","Speaker":null},{"Timestamp":"00:19:14","Token":"スペック表をニラメッコするはずなんですけど","Speaker":null},{"Timestamp":"00:19:16","Token":"でもまあ確かに詳しい人はそういうことを言いますね","Speaker":null},{"Timestamp":"00:19:19","Token":"そうそうそうずっと見てますねあれ","Speaker":null},{"Timestamp":"00:19:20","Token":"何買ったらいいって聞いたら","Speaker":null},{"Timestamp":"00:19:22","Token":"なんか聞いてもないスペックの話とかずっとされて","Speaker":null},{"Timestamp":"00:19:25","Token":"これやっぱりいいグラボ積んでるからこれ","Speaker":null},{"Timestamp":"00:19:27","Token":"マウスコンピューターのこの機種はいいグラボだから","Speaker":null},{"Timestamp":"00:19:29","Token":"結構いいよ値段の割に見て","Speaker":null},{"Timestamp":"00:19:31","Token":"グラボがもう何の略かもちょっと怪しいもんな","Speaker":null},{"Timestamp":"00:19:33","Token":"俺あの実家の近くにあった","Speaker":null},{"Timestamp":"00:19:35","Token":"グランドボールってボーリング場のこと","Speaker":null},{"Timestamp":"00:19:37","Token":"グラボって呼んでましたから","Speaker":null},{"Timestamp":"00:19:39","Token":"それじゃないですねグラフィックボードから","Speaker":null},{"Timestamp":"00:19:41","Token":"聞いたことあるわ","Speaker":null},{"Timestamp":"00:19:43","Token":"ちょっと待ってスペック表の話","Speaker":null},{"Timestamp":"00:19:45","Token":"どんだけ膨らませるんだって","Speaker":null},{"Timestamp":"00:19:46","Token":"スペック表見ててくれよ","Speaker":null},{"Timestamp":"00:19:48","Token":"元に戻します戻りますと","Speaker":null},{"Timestamp":"00:19:50","Token":"iPhoneのスペックとか見ると","Speaker":null},{"Timestamp":"00:19:51","Token":"CPU 2.4GHzとか書いてあるんですね","Speaker":null},{"Timestamp":"00:19:54","Token":"大体これみんな意味全くわからず見てて","Speaker":null},{"Timestamp":"00:19:58","Token":"Hzなんですねまず単位が","Speaker":null},{"Timestamp":"00:19:59","Token":"Hzです周波数なんで","Speaker":null},{"Timestamp":"00:20:02","Token":"数字でかければでかいほど偉い","Speaker":null},{"Timestamp":"00:20:04","Token":"っていうことだけなんとなく知ってて","Speaker":null},{"Timestamp":"00:20:06","Token":"メランデル人も多いんですけど","Speaker":null},{"Timestamp":"00:20:08","Token":"この2.4GHzって本質的には","Speaker":null},{"Timestamp":"00:20:10","Token":"さっき言った25たす13とかをこなせる回数","Speaker":null},{"Timestamp":"00:20:14","Token":"だと思ってもらっていいです","Speaker":null},{"Timestamp":"00:20:15","Token":"一番簡単な計算をこなす回数ですね","Speaker":null},{"Timestamp":"00:20:19","Token":"これ厳密には正しくないんだけど","Speaker":null},{"Timestamp":"00:20:20","Token":"一位計算にクロックとか必要だったりするんで","Speaker":null},{"Timestamp":"00:20:23","Token":"あんまり正しくないんですけど","Speaker":null},{"Timestamp":"00:20:24","Token":"変なの出てきた無視しよう","Speaker":null},{"Timestamp":"00:20:27","Token":"一旦そう思っといていただいて","Speaker":null},{"Timestamp":"00:20:28","Token":"20億回とかあれ計算回数なんだな","Speaker":null},{"Timestamp":"00:20:31","Token":"これ次からもう見れますよ","Speaker":null},{"Timestamp":"00:20:33","Token":"スペック表皆さん","Speaker":null},{"Timestamp":"00:20:34","Token":"CPU2.4GHzって書いてあったら","Speaker":null},{"Timestamp":"00:20:36","Token":"24億回計算するんだな","Speaker":null},{"Timestamp":"00:20:39","Token":"そうやって見ればいいんだ","Speaker":null},{"Timestamp":"00:20:40","Token":"GIGAって10の9乗なんで10億回ですね","Speaker":null},{"Timestamp":"00:20:43","Token":"だからスペック高いスマホとかは","Speaker":null},{"Timestamp":"00:20:45","Token":"3.0GHzとか書いてあったりして","Speaker":null},{"Timestamp":"00:20:47","Token":"GIGAだといくつだっけ10の","Speaker":null},{"Timestamp":"00:20:50","Token":"だから1GIGAが10億回なんで3GIGAは","Speaker":null},{"Timestamp":"00:20:52","Token":"そっかだから3億回","Speaker":null},{"Timestamp":"00:20:55","Token":"10億回では1GIGA","Speaker":null},{"Timestamp":"00:20:56","Token":"ごめんごめん30億回","Speaker":null},{"Timestamp":"00:20:57","Token":"俺コンピューターちょっと名乗れないわ","Speaker":null},{"Timestamp":"00:20:59","Token":"計算できてなかった","Speaker":null},{"Timestamp":"00:21:01","Token":"そうですねコンピューター失格です","Speaker":null},{"Timestamp":"00:21:05","Token":"じゃあこの話が分かれば","Speaker":null},{"Timestamp":"00:21:07","Token":"コンピューターがなぜ魔法の箱に見えるか","Speaker":null},{"Timestamp":"00:21:11","Token":"っていうことで結論がちょっと見えてくるんですけど","Speaker":null},{"Timestamp":"00:21:14","Token":"量が全然違うって何が起こるかっていうと","Speaker":null},{"Timestamp":"00:21:18","Token":"100マス計算で例えると","Speaker":null},{"Timestamp":"00:21:19","Token":"分かりやすいなと思うんですけど","Speaker":null},{"Timestamp":"00:21:21","Token":"みずほさん小学生の時やりました","Speaker":null},{"Timestamp":"00:21:23","Token":"100マス計算","Speaker":null},{"Timestamp":"00:21:24","Token":"あれやらされましたよね我々の世代","Speaker":null},{"Timestamp":"00:21:25","Token":"やりましたやりました","Speaker":null},{"Timestamp":"00:21:26","Token":"あれ今やってないんですかね","Speaker":null},{"Timestamp":"00:21:27","Token":"なんか脳にめっちゃ効くみたいな時で","Speaker":null},{"Timestamp":"00:21:29","Token":"僕が小学生の時はピークだったらしくて","Speaker":null},{"Timestamp":"00:21:32","Token":"だんだん減ってきたらしい","Speaker":null},{"Timestamp":"00:21:33","Token":"確かにねあれ俺与えられたら","Speaker":null},{"Timestamp":"00:21:35","Token":"まず1のくらいから埋めてみたいな","Speaker":null},{"Timestamp":"00:21:37","Token":"なんかあんまり本質的じゃない","Speaker":null},{"Timestamp":"00:21:38","Token":"ハックを身につける","Speaker":null},{"Timestamp":"00:21:39","Token":"そうそうそう","Speaker":null},{"Timestamp":"00:21:40","Token":"脳を使わずにやってた覚えありますね","Speaker":null},{"Timestamp":"00:21:42","Token":"そうなんですよ","Speaker":null},{"Timestamp":"00:21:43","Token":"だからある意味あるかどうかともかくとして","Speaker":null},{"Timestamp":"00:21:45","Token":"めっちゃ早いやついるじゃないですか","Speaker":null},{"Timestamp":"00:21:46","Token":"クラスに一人で","Speaker":null},{"Timestamp":"00:21:47","Token":"お前早みたいな","Speaker":null},{"Timestamp":"00:21:48","Token":"そう僕らの時って","Speaker":null},{"Timestamp":"00:21:50","Token":"できたら手上げてみたいな仕組みで","Speaker":null},{"Timestamp":"00:21:52","Token":"一番早いやつがシールとか終わられてたんですよね","Speaker":null},{"Timestamp":"00:21:54","Token":"僕らの学校からと","Speaker":null},{"Timestamp":"00:21:55","Token":"ゲームフィケーションとか","Speaker":null},{"Timestamp":"00:21:56","Token":"だけどなんか異常に早いやついて","Speaker":null},{"Timestamp":"00:21:58","Token":"僕とか書き終わる5秒前ぐらいに","Speaker":null},{"Timestamp":"00:22:00","Token":"手上げてんのにそいつに負けるんすよ","Speaker":null},{"Timestamp":"00:22:02","Token":"イカ様してるじゃん","Speaker":null},{"Timestamp":"00:22:05","Token":"さらっと言いましたけど","Speaker":null},{"Timestamp":"00:22:06","Token":"褒められたくて","Speaker":null},{"Timestamp":"00:22:07","Token":"はいはい","Speaker":null},{"Timestamp":"00:22:08","Token":"そうでもそいつ見て","Speaker":null},{"Timestamp":"00:22:11","Token":"魔法だって思いました","Speaker":null},{"Timestamp":"00:22:12","Token":"いやさすがにまあ","Speaker":null},{"Timestamp":"00:22:14","Token":"異常に早いと思うけど","Speaker":null},{"Timestamp":"00:22:17","Token":"まださすがにそこまではないですね","Speaker":null},{"Timestamp":"00:22:19","Token":"でしょだって","Speaker":null},{"Timestamp":"00:22:20","Token":"計算測とどんくらい違うかって言ったら","Speaker":null},{"Timestamp":"00:22:22","Token":"早くても2倍とか3倍とかじゃないですか","Speaker":null},{"Timestamp":"00:22:25","Token":"もしかしたら5倍ぐらい","Speaker":null},{"Timestamp":"00:22:26","Token":"早いやついるかもしれない","Speaker":null},{"Timestamp":"00:22:28","Token":"それって全然魔法に見えないんですよ","Speaker":null},{"Timestamp":"00:22:31","Token":"量的な変化にしか見えないじゃないですか","Speaker":null},{"Timestamp":"00:22:35","Token":"なんでかって言ったら","Speaker":null},{"Timestamp":"00:22:38","Token":"もし仮になんですけど","Speaker":null},{"Timestamp":"00:22:39","Token":"クラスメイトの計算早いやつが","Speaker":null},{"Timestamp":"00:22:42","Token":"水野さんが1枚終わらせてる間に","Speaker":null},{"Timestamp":"00:22:44","Token":"3枚だったら計算早い","Speaker":null},{"Timestamp":"00:22:46","Token":"水野さんが1枚終わらせてる間に","Speaker":null},{"Timestamp":"00:22:48","Token":"2000万枚終わらないといけない","Speaker":null},{"Timestamp":"00:22:51","Token":"人じゃないですよ","Speaker":null},{"Timestamp":"00:22:53","Token":"それはもう魔法じゃないですか絶対に","Speaker":null},{"Timestamp":"00:22:56","Token":"計算早いとかのレベルじゃなくて","Speaker":null},{"Timestamp":"00:22:59","Token":"用紙どっから出てきたのそもそも","Speaker":null},{"Timestamp":"00:23:01","Token":"手がもう擦り切れてますよね","Speaker":null},{"Timestamp":"00:23:04","Token":"2000万枚いつの間に","Speaker":null},{"Timestamp":"00:23:05","Token":"搬入されたのどうしてみたいな","Speaker":null},{"Timestamp":"00:23:07","Token":"なりますね","Speaker":null},{"Timestamp":"00:23:08","Token":"感じじゃないですか","Speaker":null},{"Timestamp":"00:23:10","Token":"だから2000万倍とか","Speaker":null},{"Timestamp":"00:23:12","Token":"さっきのデザインもっとでしたよね","Speaker":null},{"Timestamp":"00:23:16","Token":"魔法にしか見えなくなるんですよ","Speaker":null},{"Timestamp":"00:23:18","Token":"量的な変化ってあるところを超えると","Speaker":null},{"Timestamp":"00:23:21","Token":"質的な変化に変わるんですよ見た目上","Speaker":null},{"Timestamp":"00:23:25","Token":"というのがコンピューターが","Speaker":null},{"Timestamp":"00:23:27","Token":"魔法に見えてる理由です","Speaker":null},{"Timestamp":"00:23:30","Token":"だから想像を絶すること","Speaker":null},{"Timestamp":"00:23:31","Token":"いろいろやってくれるじゃないですか","Speaker":null},{"Timestamp":"00:23:32","Token":"youtube再生するの","Speaker":null},{"Timestamp":"00:23:34","Token":"魔法に見えてるんですけど違うんですよ","Speaker":null},{"Timestamp":"00:23:36","Token":"量がすさまじいだけです","Speaker":null},{"Timestamp":"00:23:37","Token":"じゃあ例えばyoutubeのリンクをクリックして","Speaker":null},{"Timestamp":"00:23:40","Token":"この動画見ようって押した時に","Speaker":null},{"Timestamp":"00:23:42","Token":"コンピューターめっちゃ急いで","Speaker":null},{"Timestamp":"00:23:43","Token":"100マス計算解いてる感じですか","Speaker":null},{"Timestamp":"00:23:44","Token":"そうですよ","Speaker":null},{"Timestamp":"00:23:45","Token":"そうですよ","Speaker":null},{"Timestamp":"00:23:46","Token":"そうなんだ","Speaker":null},{"Timestamp":"00:23:47","Token":"あのなんとなくイメージで","Speaker":null},{"Timestamp":"00:23:49","Token":"だからyoutubeのリンク開いて","Speaker":null},{"Timestamp":"00:23:51","Token":"再生されるまでに10億回ぐらい","Speaker":null},{"Timestamp":"00:23:53","Token":"計算されてると思ってもらえる","Speaker":null},{"Timestamp":"00:23:54","Token":"ヤバイヤバイこの人クリックした","Speaker":null},{"Timestamp":"00:23:56","Token":"うわぁ相当にしてますよあれの時","Speaker":null},{"Timestamp":"00:23:59","Token":"日本国民全員計算してみたいな状態になった","Speaker":null},{"Timestamp":"00:24:02","Token":"なんか可愛く見える","Speaker":null},{"Timestamp":"00:24:03","Token":"でしょそうなんですよ","Speaker":null},{"Timestamp":"00:24:04","Token":"楽しいんですよコンピューターは","Speaker":null},{"Timestamp":"00:24:05","Token":"なんか想像すると可愛いなこいつ","Speaker":null},{"Timestamp":"00:24:08","Token":"例えばyoutubeの押して","Speaker":null},{"Timestamp":"00:24:10","Token":"ちょっと待ってねって言ってる間に","Speaker":null},{"Timestamp":"00:24:12","Token":"やっぱ他のにしようとか","Speaker":null},{"Timestamp":"00:24:13","Token":"モトルボタン2回押したらとかやると","Speaker":null},{"Timestamp":"00:24:15","Token":"そうそうそうもうパニックですよ内側","Speaker":null},{"Timestamp":"00:24:18","Token":"うわぁあれのシーンあったらしいぞ","Speaker":null},{"Timestamp":"00:24:19","Token":"えっていうあのブラック企業の職場の","Speaker":null},{"Timestamp":"00:24:23","Token":"環境みたいな感じ","Speaker":null},{"Timestamp":"00:24:24","Token":"上司がすぐコロコロ指示変えるみたいな","Speaker":null},{"Timestamp":"00:24:26","Token":"お前これなしなぁみたいな","Speaker":null},{"Timestamp":"00:24:27","Token":"やり直しなぁみたいな","Speaker":null},{"Timestamp":"00:24:29","Token":"へぇーってかわいいですね","Speaker":null},{"Timestamp":"00:24:31","Token":"なってるんですよ","Speaker":null},{"Timestamp":"00:24:33","Token":"ファンとかわーんってうるさいですけど","Speaker":null},{"Timestamp":"00:24:34","Token":"思いっしょにさせると","Speaker":null},{"Timestamp":"00:24:35","Token":"これもコンピューターのこと分かると","Speaker":null},{"Timestamp":"00:24:36","Token":"可愛く見えてきます","Speaker":null},{"Timestamp":"00:24:37","Token":"ポリモスさんはじゃあ","Speaker":null},{"Timestamp":"00:24:38","Token":"うーんってなってる時は愛おしいんですか","Speaker":null},{"Timestamp":"00:24:41","Token":"そう頑張ってるなぁ","Speaker":null},{"Timestamp":"00:24:43","Token":"気持ちで見てます","Speaker":null},{"Timestamp":"00:24:44","Token":"ブラック企業に直すとサイコパスですね","Speaker":null},{"Timestamp":"00:24:46","Token":"サイコパス確かに","Speaker":null},{"Timestamp":"00:24:48","Token":"それ微笑ましく見てる社長ヤバイ","Speaker":null},{"Timestamp":"00:24:50","Token":"へぇーとか言ってるヤバイヤバイとか言ってる","Speaker":null},{"Timestamp":"00:24:51","Token":"頑張ってるなぁ","Speaker":null},{"Timestamp":"00:24:54","Token":"だからポリモスさんって","Speaker":null},{"Timestamp":"00:24:55","Token":"ちょっとサイコパスなとこ","Speaker":null},{"Timestamp":"00:24:56","Token":"違う違うやめて","Speaker":null},{"Timestamp":"00:24:57","Token":"コンピューターオタクのイメージ悪くすんの","Speaker":null},{"Timestamp":"00:24:59","Token":"みんないい人だから","Speaker":null},{"Timestamp":"00:25:01","Token":"失礼しました","Speaker":null},{"Timestamp":"00:25:05","Token":"ということで","Speaker":null},{"Timestamp":"00:25:07","Token":"なんで結論とまとめをしたいなと","Speaker":null},{"Timestamp":"00:25:10","Token":"思うんですけど","Speaker":null},{"Timestamp":"00:25:12","Token":"PCとかスマートフォンは","Speaker":null},{"Timestamp":"00:25:13","Token":"魔法の箱ではないんだよと","Speaker":null},{"Timestamp":"00:25:15","Token":"小人が入ってるわけじゃないんだよ","Speaker":null},{"Timestamp":"00:25:18","Token":"ただ単純な計算を20億回とかね","Speaker":null},{"Timestamp":"00:25:21","Token":"すさまじい量やってるだけなんですよ","Speaker":null},{"Timestamp":"00:25:23","Token":"100マス計算の用紙で教室を埋め尽くす奴","Speaker":null},{"Timestamp":"00:25:26","Token":"がいるだけなんですよ","Speaker":null},{"Timestamp":"00:25:29","Token":"だから物量がすごい","Speaker":null},{"Timestamp":"00:25:30","Token":"カラ質的に違って見える","Speaker":null},{"Timestamp":"00:25:32","Token":"魔法のように見えてるんだよ","Speaker":null},{"Timestamp":"00:25:34","Token":"ってことを見てきました","Speaker":null},{"Timestamp":"00:25:36","Token":"僕ねこれ最後","Speaker":null},{"Timestamp":"00:25:38","Token":"今回の台本まとめてて思ったことなんですけど","Speaker":null},{"Timestamp":"00:25:41","Token":"クラークの第三法則って知ってます?","Speaker":null},{"Timestamp":"00:25:43","Token":"知らない","Speaker":null},{"Timestamp":"00:25:44","Token":"本当?","Speaker":null},{"Timestamp":"00:25:45","Token":"これ文言は聞いたことあるんじゃないかなと","Speaker":null},{"Timestamp":"00:25:47","Token":"思うんですけど","Speaker":null},{"Timestamp":"00:25:49","Token":"十分に発達した科学技術は","Speaker":null},{"Timestamp":"00:25:51","Token":"魔法と見分けがつかない","Speaker":null},{"Timestamp":"00:25:52","Token":"もう完全に聞いたことあるわ","Speaker":null},{"Timestamp":"00:25:54","Token":"それこそ落屋洋一さんの本の帯に書いてあった","Speaker":null},{"Timestamp":"00:25:56","Token":"そうかもしれない","Speaker":null},{"Timestamp":"00:25:59","Token":"ですけどこれ提唱したのは","Speaker":null},{"Timestamp":"00:26:00","Token":"アーサーシー・クラークという有名な","Speaker":null},{"Timestamp":"00:26:02","Token":"SFの書き手です","Speaker":null},{"Timestamp":"00:26:04","Token":"2001年宇宙の旅の原作かな","Speaker":null},{"Timestamp":"00:26:07","Token":"ちょっと怪しいな","Speaker":null},{"Timestamp":"00:26:08","Token":"多分そう合ってる合ってる","Speaker":null},{"Timestamp":"00:26:11","Token":"ですね","Speaker":null},{"Timestamp":"00:26:12","Token":"のクラークが提唱した","Speaker":null},{"Timestamp":"00:26:13","Token":"これSF作家法則提唱しがち","Speaker":null},{"Timestamp":"00:26:16","Token":"って言うのある?","Speaker":null},{"Timestamp":"00:26:19","Token":"やってますけど","Speaker":null},{"Timestamp":"00:26:20","Token":"いろんな人がいろんなこと提唱するんですけど","Speaker":null},{"Timestamp":"00:26:22","Token":"クラークは科学技術の話を提唱してて","Speaker":null},{"Timestamp":"00:26:27","Token":"その3個目の法則が十分に発達した科学技術は","Speaker":null},{"Timestamp":"00:26:31","Token":"魔法と見分けがつかない","Speaker":null},{"Timestamp":"00:26:33","Token":"なんですけど","Speaker":null},{"Timestamp":"00:26:36","Token":"そうですね完全にそうですね","Speaker":null},{"Timestamp":"00:26:37","Token":"つまり計算ってすごいシンプルな動き","Speaker":null},{"Timestamp":"00:26:40","Token":"最終的には電流が0,1を足してるにすぎないんですよ","Speaker":null},{"Timestamp":"00:26:44","Token":"でも水野さんは絶対計算じゃないでしょ","Speaker":null},{"Timestamp":"00:26:46","Token":"あれは","Speaker":null},{"Timestamp":"00:26:47","Token":"YouTubeの再生ってそんな計算とかの領域じゃないじゃん","Speaker":null},{"Timestamp":"00:26:50","Token":"ってなってるわけです","Speaker":null},{"Timestamp":"00:26:52","Token":"これ十分に発達した科学技術は数的に量的に先行きすぎなんですよ","Speaker":null},{"Timestamp":"00:26:59","Token":"半端ない先行っちゃってるせいで","Speaker":null},{"Timestamp":"00:27:02","Token":"魔法に見えてる","Speaker":null},{"Timestamp":"00:27:04","Token":"魔法なわけないぞ科学技術なんで","Speaker":null},{"Timestamp":"00:27:06","Token":"全部ブレイクダウンしてくればただの計算とかね","Speaker":null},{"Timestamp":"00:27:09","Token":"それこそただの電流とかになるわけ","Speaker":null},{"Timestamp":"00:27:11","Token":"でもそうじゃなく見えてる","Speaker":null},{"Timestamp":"00:27:14","Token":"量的な進化がすさまじいから","Speaker":null},{"Timestamp":"00:27:17","Token":"だしクラークの言いたかったことってそれなんじゃないかな","Speaker":null},{"Timestamp":"00:27:19","Token":"なるほどね","Speaker":null},{"Timestamp":"00:27:20","Token":"思ったんですよね","Speaker":null},{"Timestamp":"00:27:21","Token":"量的な進化が質的な進化に見えちゃうよね","Speaker":null},{"Timestamp":"00:27:24","Token":"そう翻訳するとわかりやすいですね","Speaker":null},{"Timestamp":"00:27:26","Token":"っていうことを指摘したのがこの第三法則なんじゃないかな","Speaker":null},{"Timestamp":"00:27:29","Token":"ということを思った","Speaker":null},{"Timestamp":"00:27:30","Token":"っていうのが今回の結論","Speaker":null},{"Timestamp":"00:27:32","Token":"いい話ですね","Speaker":null},{"Timestamp":"00:27:35","Token":"というのが僕から言いたいことなんですけど","Speaker":null},{"Timestamp":"00:27:36","Token":"どうですか水野さん初めての試みなんですけど","Speaker":null},{"Timestamp":"00:27:39","Token":"面白いですね","Speaker":null},{"Timestamp":"00:27:40","Token":"ほんと?","Speaker":null},{"Timestamp":"00:27:41","Token":"僕も今なんかね初心を取り返してる感じがあって","Speaker":null},{"Timestamp":"00:27:45","Token":"どういうことですか","Speaker":null},{"Timestamp":"00:27:47","Token":"最近何でも難しい話にしたいがちだったんですけど","Speaker":null},{"Timestamp":"00:27:51","Token":"これぐらいの温度感いいなっていう","Speaker":null},{"Timestamp":"00:27:53","Token":"ちゃちゃ入れやすいな","Speaker":null},{"Timestamp":"00:27:54","Token":"いいですよね","Speaker":null},{"Timestamp":"00:27:56","Token":"今1回目の収録の今ね","Speaker":null},{"Timestamp":"00:27:59","Token":"情景が戻ってきてるんですよ","Speaker":null},{"Timestamp":"00:28:02","Token":"単語ってすごいですよねとか言って","Speaker":null},{"Timestamp":"00:28:04","Token":"第1回良かったですね","Speaker":null},{"Timestamp":"00:28:05","Token":"ちゃちゃ入れやすくて","Speaker":null},{"Timestamp":"00:28:07","Token":"イルカって喋ってんのかなみたいな","Speaker":null},{"Timestamp":"00:28:10","Token":"今でもイルカって喋ってるかっていう","Speaker":null},{"Timestamp":"00:28:12","Token":"トークテーマを与えられたら","Speaker":null},{"Timestamp":"00:28:14","Token":"すごい勉強してこないと","Speaker":null},{"Timestamp":"00:28:15","Token":"喋れないなって気がするんですよ","Speaker":null},{"Timestamp":"00:28:17","Token":"最新の研究によると","Speaker":null},{"Timestamp":"00:28:18","Token":"広報こういうのが発表されてて","Speaker":null},{"Timestamp":"00:28:20","Token":"動物学者の方からも持ってきて","Speaker":null},{"Timestamp":"00:28:22","Token":"言語学者ってどうやって言語を定義してんだっけ","Speaker":null},{"Timestamp":"00:28:23","Token":"みたいなのをやってんだけど","Speaker":null},{"Timestamp":"00:28:27","Token":"ちょっとそういう粗いけれども","Speaker":null},{"Timestamp":"00:28:30","Token":"キャッチーな話みたいなのの","Speaker":null},{"Timestamp":"00:28:31","Token":"感覚をちょっと思い出しました","Speaker":null},{"Timestamp":"00:28:33","Token":"良かったです","Speaker":null},{"Timestamp":"00:28:35","Token":"ということで今回は終わりにしたいと思います","Speaker":null},{"Timestamp":"00:28:38","Token":"引き続き第2回ではですね","Speaker":null},{"Timestamp":"00:28:40","Token":"エンジニアも魔法使いじゃないんだよと","Speaker":null},{"Timestamp":"00:28:43","Token":"プログラマーって何やってんの","Speaker":null},{"Timestamp":"00:28:44","Token":"みたいな話をしていきたいと思います","Speaker":null},{"Timestamp":"00:28:46","Token":"よろしくお願いします","Speaker":null},{"Timestamp":"00:28:47","Token":"じゃあ今回も終わりにしましょう","Speaker":null},{"Timestamp":"00:28:48","Token":"ありがとうございました","Speaker":null},{"Timestamp":"00:28:52","Token":"このラジオは1階の言語オタクが","Speaker":null},{"Timestamp":"00:28:55","Token":"ゆるく楽しく言語の面白さを語るラジオです","Speaker":null},{"Timestamp":"00:28:58","Token":"自由気ままな言語トークですので","Speaker":null},{"Timestamp":"00:29:01","Token":"厳密な交渉は行っておりません","Speaker":null},{"Timestamp":"00:29:03","Token":"内容には諸説あります","Speaker":null},{"Timestamp":"00:29:05","Token":"ご了承の上お聞きください","Speaker":null}]